{
 "actions": [],
 "allow_rename": 1,
 "creation": "2022-04-16 04:54:45.935754",
 "doctype": "DocType",
 "editable_grid": 1,
 "engine": "InnoDB",
 "field_order": [
  "no_material_request",
  "material_cor",
  "no_spk",
  "kadar",
  "column_break_5",
  "qty",
  "berat",
  "berat_cor",
  "pohon_id",
  "no_pohon",
  "section_break_10",
  "batch_cb_1",
  "batch_cb_2",
  "batch_cb_3",
  "column_break_14",
  "berat_batch_1",
  "berat_batch_2",
  "berat_batch_3",
  "total_berat_batch"
 ],
 "fields": [
  {
   "fieldname": "no_material_request",
   "fieldtype": "Link",
   "label": "No Material Request",
   "options": "Material Request"
  },
  {
   "columns": 2,
   "fieldname": "material_cor",
   "fieldtype": "Link",
   "in_list_view": 1,
   "label": "Material Cor",
   "options": "Item"
  },
  {
   "columns": 2,
   "fieldname": "no_spk",
   "fieldtype": "Data",
   "in_list_view": 1,
   "label": "No SPK"
  },
  {
   "columns": 2,
   "fieldname": "kadar",
   "fieldtype": "Link",
   "in_list_view": 1,
   "label": "Kadar",
   "options": "Data Logam"
  },
  {
   "fieldname": "column_break_5",
   "fieldtype": "Column Break"
  },
  {
   "columns": 1,
   "fieldname": "qty",
   "fieldtype": "Int",
   "in_list_view": 1,
   "label": "Qty"
  },
  {
   "columns": 1,
   "fieldname": "berat",
   "fieldtype": "Float",
   "in_list_view": 1,
   "label": "Berat"
  },
  {
   "fieldname": "pohon_id",
   "fieldtype": "Data",
   "label": "Pohon ID"
  },
  {
   "columns": 1,
   "fieldname": "no_pohon",
   "fieldtype": "Data",
   "in_list_view": 1,
   "label": "No Pohon"
  },
  {
   "fieldname": "section_break_10",
   "fieldtype": "Section Break",
   "label": "Data Batch CB"
  },
  {
   "fieldname": "batch_cb_1",
   "fieldtype": "Data",
   "label": "Batch Cb 1"
  },
  {
   "fieldname": "batch_cb_2",
   "fieldtype": "Data",
   "label": "Batch Cb 2"
  },
  {
   "fieldname": "batch_cb_3",
   "fieldtype": "Data",
   "label": "Batch Cb 3"
  },
  {
   "fieldname": "column_break_14",
   "fieldtype": "Column Break"
  },
  {
   "fieldname": "berat_batch_1",
   "fieldtype": "Float",
   "label": "Berat Batch 1"
  },
  {
   "fieldname": "berat_batch_2",
   "fieldtype": "Float",
   "label": "Berat Batch 2 "
  },
  {
   "fieldname": "berat_batch_3",
   "fieldtype": "Float",
   "label": "Berat Batch 3"
  },
  {
   "fieldname": "total_berat_batch",
   "fieldtype": "Float",
   "label": "Total Berat Batch"
  },
  {
   "fieldname": "berat_cor",
   "fieldtype": "Float",
   "label": "Berat Cor"
  }
 ],
 "index_web_pages_for_search": 1,
 "istable": 1,
 "links": [],
 "modified": "2022-04-16 06:10:10.725299",
 "modified_by": "Administrator",
 "module": "Lestari",
 "name": "Form Hasil Job Card Cor",
 "owner": "Administrator",
 "permissions": [],
 "sort_field": "modified",
 "sort_order": "DESC"
}